{"id": "politifact13747", "label": 0, "url": "https://web.archive.org/web/20170205045142/http://departedmedia.com/bill-gates-i-think-donald-trump-will-go-down-to-history-as-one-of-the-greatest-presidents-just-like-reagan/", "title": "Bill Gates: “I think Donald Trump will go down to history as one of the greatest presidents, just like Reagan.”", "text": "Bill Gates: “I think Donald Trump  will go down to history as one of the greatest presidents, just like Reagan.” Heisenberg 7 hours ago News Comments Off on Bill Gates: “I think Donald Trump  will go down to history as one of the greatest presidents, just like Reagan.” Your Vote Matters! Vote Now! Loading... Best free WordPress theme Share this: Click to share on Twitter (Opens in new window) Click to share on Facebook (Opens in new window) Click to share on Google+ (Opens in new window) Like this: Like Loading... 2017-02-05 Heisenberg"}